{
  "updated": "2026-07-24T05:56:19.904218Z",
  "fii_dii": {
    "available": true,
    "source": "NSE provisional",
    "date": "23-Jul-2026",
    "fii": {
      "buy": 11472.08,
      "sell": 14471.31,
      "net": -2999.23
    },
    "dii": {
      "buy": 16575.3,
      "sell": 13628.16,
      "net": 2947.14
    },
    "net_combined": -52.09
  },
  "corporate": [
    {
      "date": "2026-07-25",
      "date_str": "25 Jul",
      "symbol": "3PLAND",
      "company": "3P Land Holdings Limited",
      "purpose": "Financial Results"
    },
    {
      "date": "2026-07-25",
      "date_str": "25 Jul",
      "symbol": "AUBANK",
      "company": "AU Small Finance Bank Limited",
      "purpose": "Financial Results"
    },
    {
      "date": "2026-07-25",
      "date_str": "25 Jul",
      "symbol": "BIRLACORPN",
      "company": "Birla Corporation Limited",
      "purpose": "Financial Results"
    },
    {
      "date": "2026-07-25",
      "date_str": "25 Jul",
      "symbol": "DODLA",
      "company": "Dodla Dairy Limited",
      "purpose": "Financial Results"
    },
    {
      "date": "2026-07-25",
      "date_str": "25 Jul",
      "symbol": "EXXARO",
      "company": "Exxaro Tiles Limited",
      "purpose": "Financial Results"
    },
    {
      "date": "2026-07-25",
      "date_str": "25 Jul",
      "symbol": "FCSSOFT",
      "company": "FCS Software Solutions Limited",
      "purpose": "Financial Results"
    },
    {
      "date": "2026-07-25",
      "date_str": "25 Jul",
      "symbol": "FIVESTAR",
      "company": "Five-Star Business Finance Limited",
      "purpose": "Financial Results"
    },
    {
      "date": "2026-07-25",
      "date_str": "25 Jul",
      "symbol": "IDFCFIRSTB",
      "company": "IDFC First Bank Limited",
      "purpose": "Fund Raising"
    },
    {
      "date": "2026-07-25",
      "date_str": "25 Jul",
      "symbol": "IDFCFIRSTB",
      "company": "IDFC First Bank Limited",
      "purpose": "Financial Results"
    },
    {
      "date": "2026-07-25",
      "date_str": "25 Jul",
      "symbol": "MANYAVAR",
      "company": "Vedant Fashions Limited",
      "purpose": "Financial Results"
    },
    {
      "date": "2026-07-25",
      "date_str": "25 Jul",
      "symbol": "NILAINFRA",
      "company": "Nila Infrastructures Limited",
      "purpose": "Financial Results"
    },
    {
      "date": "2026-07-25",
      "date_str": "25 Jul",
      "symbol": "PRUDENT",
      "company": "Prudent Corporate Advisory Services Li",
      "purpose": "Financial Results"
    },
    {
      "date": "2026-07-25",
      "date_str": "25 Jul",
      "symbol": "SABEVENTS",
      "company": "Sab Events & Governance Now Media Limi",
      "purpose": "Other business matters"
    },
    {
      "date": "2026-07-25",
      "date_str": "25 Jul",
      "symbol": "SBFC",
      "company": "SBFC Finance Limited",
      "purpose": "Financial Results"
    },
    {
      "date": "2026-07-25",
      "date_str": "25 Jul",
      "symbol": "SESHAPAPER",
      "company": "Seshasayee Paper and Boards Limited",
      "purpose": "Financial Results"
    },
    {
      "date": "2026-07-25",
      "date_str": "25 Jul",
      "symbol": "SURANASOL",
      "company": "Surana Solar Limited",
      "purpose": "Financial Results"
    },
    {
      "date": "2026-07-25",
      "date_str": "25 Jul",
      "symbol": "ZENTEC",
      "company": "Zen Technologies Limited",
      "purpose": "Financial Results"
    },
    {
      "date": "2026-07-26",
      "date_str": "26 Jul",
      "symbol": "SMCGLOBAL",
      "company": "SMC Global Securities Limited",
      "purpose": "Financial Results/Fund Raising"
    },
    {
      "date": "2026-07-27",
      "date_str": "27 Jul",
      "symbol": "AASTHA",
      "company": "Aastha Spintex Limited",
      "purpose": "Financial Results"
    },
    {
      "date": "2026-07-27",
      "date_str": "27 Jul",
      "symbol": "ACL",
      "company": "Andhra Cements Limited",
      "purpose": "Financial Results"
    }
  ]
}