{
  "NIFTY": {
    "symbol": "NIFTY",
    "available": true,
    "spot": 24211.0,
    "expiry": "2026-07-14",
    "pcr": 1.62,
    "total_ce_oi": 144214720,
    "total_pe_oi": 233932335,
    "max_pain": 24200.0,
    "support": 24000.0,
    "resistance": 24500.0,
    "atm_iv": null,
    "chain": [
      {
        "strike": 23450.0,
        "ceOI": 17940,
        "peOI": 2540785
      },
      {
        "strike": 23500.0,
        "ceOI": 189085,
        "peOI": 11302200
      },
      {
        "strike": 23550.0,
        "ceOI": 32760,
        "peOI": 3247140
      },
      {
        "strike": 23600.0,
        "ceOI": 78780,
        "peOI": 9458150
      },
      {
        "strike": 23650.0,
        "ceOI": 39910,
        "peOI": 5764915
      },
      {
        "strike": 23700.0,
        "ceOI": 205075,
        "peOI": 10657270
      },
      {
        "strike": 23750.0,
        "ceOI": 85150,
        "peOI": 6297460
      },
      {
        "strike": 23800.0,
        "ceOI": 475085,
        "peOI": 10301460
      },
      {
        "strike": 23850.0,
        "ceOI": 254800,
        "peOI": 5036070
      },
      {
        "strike": 23900.0,
        "ceOI": 769535,
        "peOI": 9059375
      },
      {
        "strike": 23950.0,
        "ceOI": 362960,
        "peOI": 6601400
      },
      {
        "strike": 24000.0,
        "ceOI": 3260530,
        "peOI": 19788210
      },
      {
        "strike": 24050.0,
        "ceOI": 1156740,
        "peOI": 8856120
      },
      {
        "strike": 24100.0,
        "ceOI": 3155230,
        "peOI": 13635375
      },
      {
        "strike": 24150.0,
        "ceOI": 3862170,
        "peOI": 10457525
      },
      {
        "strike": 24200.0,
        "ceOI": 9105850,
        "peOI": 12237810
      },
      {
        "strike": 24250.0,
        "ceOI": 6511505,
        "peOI": 3887715
      },
      {
        "strike": 24300.0,
        "ceOI": 9598420,
        "peOI": 2864420
      },
      {
        "strike": 24350.0,
        "ceOI": 5159700,
        "peOI": 449800
      },
      {
        "strike": 24400.0,
        "ceOI": 8387990,
        "peOI": 835445
      },
      {
        "strike": 24450.0,
        "ceOI": 5588050,
        "peOI": 250835
      },
      {
        "strike": 24500.0,
        "ceOI": 17521205,
        "peOI": 3524430
      },
      {
        "strike": 24550.0,
        "ceOI": 3805100,
        "peOI": 74815
      },
      {
        "strike": 24600.0,
        "ceOI": 8270730,
        "peOI": 365300
      },
      {
        "strike": 24650.0,
        "ceOI": 3288545,
        "peOI": 61295
      },
      {
        "strike": 24700.0,
        "ceOI": 7834255,
        "peOI": 122850
      },
      {
        "strike": 24750.0,
        "ceOI": 1968135,
        "peOI": 20995
      },
      {
        "strike": 24800.0,
        "ceOI": 5925465,
        "peOI": 75920
      },
      {
        "strike": 24850.0,
        "ceOI": 1309230,
        "peOI": 23530
      },
      {
        "strike": 24900.0,
        "ceOI": 3217890,
        "peOI": 29900
      },
      {
        "strike": 24950.0,
        "ceOI": 986830,
        "peOI": 20930
      }
    ],
    "source": "Moneycontrol (cached)"
  },
  "BANKNIFTY": {
    "symbol": "BANKNIFTY",
    "available": true,
    "spot": 58131.45,
    "expiry": "2026-07-28",
    "pcr": 0.97,
    "total_ce_oi": 13968810,
    "total_pe_oi": 13572210,
    "max_pain": 58100.0,
    "support": 58000.0,
    "resistance": 59000.0,
    "atm_iv": null,
    "chain": [
      {
        "strike": 50600.0,
        "ceOI": 0,
        "peOI": 3090
      },
      {
        "strike": 50700.0,
        "ceOI": 0,
        "peOI": 4230
      },
      {
        "strike": 50800.0,
        "ceOI": 0,
        "peOI": 3750
      },
      {
        "strike": 50900.0,
        "ceOI": 0,
        "peOI": 8040
      },
      {
        "strike": 51000.0,
        "ceOI": 10320,
        "peOI": 222840
      },
      {
        "strike": 51100.0,
        "ceOI": 0,
        "peOI": 2640
      },
      {
        "strike": 51200.0,
        "ceOI": 0,
        "peOI": 7530
      },
      {
        "strike": 51300.0,
        "ceOI": 0,
        "peOI": 2910
      },
      {
        "strike": 51400.0,
        "ceOI": 0,
        "peOI": 2430
      },
      {
        "strike": 51500.0,
        "ceOI": 600,
        "peOI": 60540
      },
      {
        "strike": 51600.0,
        "ceOI": 0,
        "peOI": 1860
      },
      {
        "strike": 51700.0,
        "ceOI": 0,
        "peOI": 3360
      },
      {
        "strike": 51800.0,
        "ceOI": 0,
        "peOI": 3630
      },
      {
        "strike": 51900.0,
        "ceOI": 0,
        "peOI": 4200
      },
      {
        "strike": 52000.0,
        "ceOI": 35490,
        "peOI": 330630
      },
      {
        "strike": 52100.0,
        "ceOI": 0,
        "peOI": 4350
      },
      {
        "strike": 52200.0,
        "ceOI": 0,
        "peOI": 3120
      },
      {
        "strike": 52300.0,
        "ceOI": 0,
        "peOI": 3480
      },
      {
        "strike": 52400.0,
        "ceOI": 0,
        "peOI": 4740
      },
      {
        "strike": 52500.0,
        "ceOI": 3000,
        "peOI": 82650
      },
      {
        "strike": 52600.0,
        "ceOI": 90,
        "peOI": 6630
      },
      {
        "strike": 52700.0,
        "ceOI": 180,
        "peOI": 5460
      },
      {
        "strike": 52800.0,
        "ceOI": 480,
        "peOI": 7260
      },
      {
        "strike": 52900.0,
        "ceOI": 150,
        "peOI": 5760
      },
      {
        "strike": 53000.0,
        "ceOI": 58200,
        "peOI": 519480
      },
      {
        "strike": 53100.0,
        "ceOI": 210,
        "peOI": 2760
      },
      {
        "strike": 53200.0,
        "ceOI": 300,
        "peOI": 13920
      },
      {
        "strike": 53300.0,
        "ceOI": 540,
        "peOI": 9960
      },
      {
        "strike": 53400.0,
        "ceOI": 450,
        "peOI": 8670
      },
      {
        "strike": 53500.0,
        "ceOI": 12030,
        "peOI": 197280
      },
      {
        "strike": 53600.0,
        "ceOI": 630,
        "peOI": 18060
      },
      {
        "strike": 53700.0,
        "ceOI": 450,
        "peOI": 20130
      },
      {
        "strike": 53800.0,
        "ceOI": 660,
        "peOI": 16170
      },
      {
        "strike": 53900.0,
        "ceOI": 1230,
        "peOI": 9180
      },
      {
        "strike": 54000.0,
        "ceOI": 75000,
        "peOI": 591000
      },
      {
        "strike": 54100.0,
        "ceOI": 780,
        "peOI": 15510
      },
      {
        "strike": 54200.0,
        "ceOI": 990,
        "peOI": 25950
      },
      {
        "strike": 54300.0,
        "ceOI": 510,
        "peOI": 17400
      },
      {
        "strike": 54400.0,
        "ceOI": 750,
        "peOI": 35460
      },
      {
        "strike": 54500.0,
        "ceOI": 14880,
        "peOI": 214470
      },
      {
        "strike": 54600.0,
        "ceOI": 1530,
        "peOI": 13680
      },
      {
        "strike": 54700.0,
        "ceOI": 4710,
        "peOI": 27750
      },
      {
        "strike": 54800.0,
        "ceOI": 630,
        "peOI": 26130
      },
      {
        "strike": 54900.0,
        "ceOI": 660,
        "peOI": 34890
      },
      {
        "strike": 55000.0,
        "ceOI": 100920,
        "peOI": 697890
      },
      {
        "strike": 55100.0,
        "ceOI": 4620,
        "peOI": 37740
      },
      {
        "strike": 55200.0,
        "ceOI": 2160,
        "peOI": 36150
      },
      {
        "strike": 55300.0,
        "ceOI": 3900,
        "peOI": 28320
      },
      {
        "strike": 55400.0,
        "ceOI": 2550,
        "peOI": 19860
      },
      {
        "strike": 55500.0,
        "ceOI": 38610,
        "peOI": 283530
      },
      {
        "strike": 55600.0,
        "ceOI": 2370,
        "peOI": 31110
      },
      {
        "strike": 55700.0,
        "ceOI": 1350,
        "peOI": 44610
      },
      {
        "strike": 55800.0,
        "ceOI": 2550,
        "peOI": 37410
      },
      {
        "strike": 55900.0,
        "ceOI": 2280,
        "peOI": 44730
      },
      {
        "strike": 56000.0,
        "ceOI": 100590,
        "peOI": 636210
      },
      {
        "strike": 56100.0,
        "ceOI": 1980,
        "peOI": 29460
      },
      {
        "strike": 56200.0,
        "ceOI": 2370,
        "peOI": 41610
      },
      {
        "strike": 56300.0,
        "ceOI": 3690,
        "peOI": 25650
      },
      {
        "strike": 56400.0,
        "ceOI": 11910,
        "peOI": 38340
      },
      {
        "strike": 56500.0,
        "ceOI": 62190,
        "peOI": 422760
      },
      {
        "strike": 56600.0,
        "ceOI": 17130,
        "peOI": 80670
      },
      {
        "strike": 56700.0,
        "ceOI": 79860,
        "peOI": 92400
      },
      {
        "strike": 56800.0,
        "ceOI": 76710,
        "peOI": 113760
      },
      {
        "strike": 56900.0,
        "ceOI": 37230,
        "peOI": 90840
      },
      {
        "strike": 57000.0,
        "ceOI": 393870,
        "peOI": 775680
      },
      {
        "strike": 57100.0,
        "ceOI": 24690,
        "peOI": 81810
      },
      {
        "strike": 57200.0,
        "ceOI": 38100,
        "peOI": 136230
      },
      {
        "strike": 57300.0,
        "ceOI": 49470,
        "peOI": 89550
      },
      {
        "strike": 57400.0,
        "ceOI": 70260,
        "peOI": 90630
      },
      {
        "strike": 57500.0,
        "ceOI": 342240,
        "peOI": 520050
      },
      {
        "strike": 57600.0,
        "ceOI": 88560,
        "peOI": 125310
      },
      {
        "strike": 57700.0,
        "ceOI": 68940,
        "peOI": 140970
      },
      {
        "strike": 57800.0,
        "ceOI": 86250,
        "peOI": 175110
      },
      {
        "strike": 57900.0,
        "ceOI": 108960,
        "peOI": 138330
      },
      {
        "strike": 58000.0,
        "ceOI": 1258560,
        "peOI": 1323300
      },
      {
        "strike": 58100.0,
        "ceOI": 170430,
        "peOI": 127470
      },
      {
        "strike": 58200.0,
        "ceOI": 272760,
        "peOI": 181560
      },
      {
        "strike": 58300.0,
        "ceOI": 210270,
        "peOI": 123750
      },
      {
        "strike": 58400.0,
        "ceOI": 171120,
        "peOI": 133740
      },
      {
        "strike": 58500.0,
        "ceOI": 762720,
        "peOI": 482400
      },
      {
        "strike": 58600.0,
        "ceOI": 249600,
        "peOI": 63390
      },
      {
        "strike": 58700.0,
        "ceOI": 218580,
        "peOI": 51930
      },
      {
        "strike": 58800.0,
        "ceOI": 111840,
        "peOI": 50070
      },
      {
        "strike": 58900.0,
        "ceOI": 107220,
        "peOI": 43020
      },
      {
        "strike": 59000.0,
        "ceOI": 2071980,
        "peOI": 1257330
      },
      {
        "strike": 59100.0,
        "ceOI": 68460,
        "peOI": 16890
      },
      {
        "strike": 59200.0,
        "ceOI": 97440,
        "peOI": 6960
      },
      {
        "strike": 59300.0,
        "ceOI": 84510,
        "peOI": 7470
      },
      {
        "strike": 59400.0,
        "ceOI": 68370,
        "peOI": 4650
      },
      {
        "strike": 59500.0,
        "ceOI": 419670,
        "peOI": 42270
      },
      {
        "strike": 59600.0,
        "ceOI": 88320,
        "peOI": 2190
      },
      {
        "strike": 59700.0,
        "ceOI": 58740,
        "peOI": 2220
      },
      {
        "strike": 59800.0,
        "ceOI": 60960,
        "peOI": 1230
      },
      {
        "strike": 59900.0,
        "ceOI": 62400,
        "peOI": 720
      },
      {
        "strike": 60000.0,
        "ceOI": 1583910,
        "peOI": 730320
      },
      {
        "strike": 60100.0,
        "ceOI": 52140,
        "peOI": 1380
      },
      {
        "strike": 60200.0,
        "ceOI": 99780,
        "peOI": 270
      },
      {
        "strike": 60300.0,
        "ceOI": 113550,
        "peOI": 120
      },
      {
        "strike": 60400.0,
        "ceOI": 44610,
        "peOI": 180
      },
      {
        "strike": 60500.0,
        "ceOI": 375120,
        "peOI": 22410
      },
      {
        "strike": 60600.0,
        "ceOI": 37890,
        "peOI": 150
      },
      {
        "strike": 60700.0,
        "ceOI": 23760,
        "peOI": 60
      },
      {
        "strike": 60800.0,
        "ceOI": 31230,
        "peOI": 570
      },
      {
        "strike": 60900.0,
        "ceOI": 21000,
        "peOI": 120
      },
      {
        "strike": 61000.0,
        "ceOI": 583290,
        "peOI": 78060
      },
      {
        "strike": 61100.0,
        "ceOI": 23220,
        "peOI": 150
      },
      {
        "strike": 61200.0,
        "ceOI": 30570,
        "peOI": 120
      },
      {
        "strike": 61300.0,
        "ceOI": 0,
        "peOI": 120
      },
      {
        "strike": 61400.0,
        "ceOI": 18900,
        "peOI": 240
      },
      {
        "strike": 61500.0,
        "ceOI": 252120,
        "peOI": 18690
      },
      {
        "strike": 61600.0,
        "ceOI": 8490,
        "peOI": 0
      },
      {
        "strike": 61800.0,
        "ceOI": 25230,
        "peOI": 0
      },
      {
        "strike": 62000.0,
        "ceOI": 686460,
        "peOI": 81870
      },
      {
        "strike": 62100.0,
        "ceOI": 1380,
        "peOI": 30
      },
      {
        "strike": 62200.0,
        "ceOI": 1890,
        "peOI": 1800
      },
      {
        "strike": 62300.0,
        "ceOI": 19920,
        "peOI": 0
      },
      {
        "strike": 62400.0,
        "ceOI": 2580,
        "peOI": 0
      },
      {
        "strike": 62500.0,
        "ceOI": 128370,
        "peOI": 1110
      },
      {
        "strike": 62600.0,
        "ceOI": 1800,
        "peOI": 0
      },
      {
        "strike": 62700.0,
        "ceOI": 870,
        "peOI": 0
      },
      {
        "strike": 62800.0,
        "ceOI": 720,
        "peOI": 0
      },
      {
        "strike": 62900.0,
        "ceOI": 2340,
        "peOI": 0
      },
      {
        "strike": 63000.0,
        "ceOI": 423360,
        "peOI": 84330
      },
      {
        "strike": 63100.0,
        "ceOI": 3210,
        "peOI": 0
      },
      {
        "strike": 63200.0,
        "ceOI": 1140,
        "peOI": 0
      },
      {
        "strike": 63300.0,
        "ceOI": 540,
        "peOI": 0
      },
      {
        "strike": 63400.0,
        "ceOI": 1530,
        "peOI": 0
      },
      {
        "strike": 63500.0,
        "ceOI": 60390,
        "peOI": 4710
      },
      {
        "strike": 63600.0,
        "ceOI": 600,
        "peOI": 0
      },
      {
        "strike": 63700.0,
        "ceOI": 15990,
        "peOI": 0
      },
      {
        "strike": 63800.0,
        "ceOI": 2640,
        "peOI": 0
      },
      {
        "strike": 64000.0,
        "ceOI": 120120,
        "peOI": 2490
      },
      {
        "strike": 64500.0,
        "ceOI": 20760,
        "peOI": 180
      },
      {
        "strike": 65000.0,
        "ceOI": 176520,
        "peOI": 75180
      },
      {
        "strike": 65500.0,
        "ceOI": 112350,
        "peOI": 7680
      }
    ],
    "source": "Moneycontrol (cached)"
  },
  "updated": "2026-07-14T06:17:28.924905Z"
}